MANIFEST.in
README.md
README.rst
setup.cfg
setup.py
all_badge/__init__.py
all_badge/__main__.py
all_badge.egg-info/PKG-INFO
all_badge.egg-info/SOURCES.txt
all_badge.egg-info/dependency_links.txt
all_badge.egg-info/entry_points.txt
all_badge.egg-info/top_level.txt
all_badge.egg-info/zip-safe
all_badge/templates/flat-square.svg
all_badge/templates/flat.svg
all_badge/templates/for-the-badge.svg