Metadata-Version: 1.1
Name: all-badge
Version: 0.1.3
Summary: Generate badges for Coverage.py, Git tags and custom.
Home-page: https://github.com/CarlosMart626/all-badge
Author: Carlos Martinez
Author-email: me@carlosmart.co
License: MIT
Keywords: coverage badge shield git custom badge styles
Platform: UNKNOWN
Classifier: Development Status :: 4 - Beta
Classifier: Environment :: Console
Classifier: License :: OSI Approved :: MIT License
Classifier: Operating System :: OS Independent
Classifier: Programming Language :: Python :: 2
Classifier: Programming Language :: Python :: 2.7
Classifier: Programming Language :: Python :: 3
Classifier: Topic :: Software Development :: Testing
